dc1d/__init__.py
dc1d/nn.py
dc1d/ops.py
dc1d-0.0.7.dist-info/METADATA
dc1d-0.0.7.dist-info/WHEEL
dc1d-0.0.7.dist-info/licenses/LICENSE
dc1d-0.0.7.dist-info/RECORD
