Metadata-Version: 2.1
Name: dc1d
Version: 0.0.7
Summary: A PyTorch implementation of 1D deformable convolution
Project-URL: Homepage, https://github.com/jwr1995/dc1d
Project-URL: Bug Tracker, https://github.com/jwr1995/dc1d/issues
Author-email: William Ravenscroft <jwravenscroft1@sheffield.ac.uk>
License: MIT License
License-File: LICENSE
Classifier: License :: OSI Approved :: MIT License
Classifier: Operating System :: OS Independent
Classifier: Programming Language :: Python :: 3
Requires-Python: >=3.8
